README.rst
float2words.py
setup.py
float2words.egg-info/PKG-INFO
float2words.egg-info/SOURCES.txt
float2words.egg-info/dependency_links.txt
float2words.egg-info/requires.txt
float2words.egg-info/top_level.txt